patelier/__init__.py
patelier/pateliercore.py
patelier/data/patelierzero.py
patelier/data/zero/patelierzero.html
patelier/data/zero/patelier-assets/patelier.css
patelier/data/zero/patelier-assets/patelier.gif
patelier/data/zero/patelier-assets/patelier.ico
patelier/data/zero/patelier-assets/patelier.js
patelier/data/zero/patelier-assets/patelier.png
patelier/data/zero/patelier-assets/pateliertc.png
patelier/data/zero/patelier-assets/patelierzero.j
patelier-0.0.2.dev4.dist-info/LICENSE.txt
patelier-0.0.2.dev4.dist-info/METADATA
patelier-0.0.2.dev4.dist-info/WHEEL
patelier-0.0.2.dev4.dist-info/entry_points.txt
patelier-0.0.2.dev4.dist-info/top_level.txt
patelier-0.0.2.dev4.dist-info/RECORD
