Metadata-Version: 2.1
Name: patelier
Version: 0.0.2.dev4
Summary: A Japanese text-line analyzing package
Home-page: https://pypi.org/project/patelier
Author: K2UNIT
Author-email: patelier@zeus.eonet.ne.jp
License: MIT License
Keywords: Japanese text lines,Japanese text-line analyzing
Platform: Windows
Classifier: Development Status :: 2 - Pre-Alpha
Classifier: Intended Audience :: End Users/Desktop
Classifier: License :: OSI Approved :: MIT License
Classifier: Natural Language :: Japanese
Classifier: Operating System :: Microsoft :: Windows :: Windows 10
Classifier: Programming Language :: Python :: 3.7
Classifier: Topic :: Utilities
Requires-Dist: eel
Requires-Dist: mecab-python3
Requires-Dist: natsort
Requires-Dist: regex
Requires-Dist: pyperclip
Requires-Dist: python-docx
Requires-Dist: pywin32
